<?xml version="1.0" encoding="utf-8"?><Airport xmlns:xsi="http://www.w3.org/2001/XMLSchema-instance" xmlns:xsd="http://www.w3.org/2001/XMLSchema"><RunwayLength>1200</RunwayLength><RunwayWidth>300</RunwayWidth><NumberOfRunways>5</NumberOfRunways><Name>Fvf</Name><City>Minsk</City></Airport><?xml version="1.0" encoding="utf-8"?><Airport xmlns:xsi="http://www.w3.org/2001/XMLSchema-instance" xmlns:xsd="http://www.w3.org/2001/XMLSchema"><RunwayLength>1000</RunwayLength><RunwayWidth>280</RunwayWidth><NumberOfRunways>3</NumberOfRunways><Name>Vbf</Name><City>Brest</City></Airport><?xml version="1.0" encoding="utf-8"?><Airport xmlns:xsi="http://www.w3.org/2001/XMLSchema-instance" xmlns:xsd="http://www.w3.org/2001/XMLSchema"><RunwayLength>1300</RunwayLength><RunwayWidth>320</RunwayWidth><NumberOfRunways>5</NumberOfRunways><Name>Bfd</Name><City>Moscow</City></Airport><?xml version="1.0" encoding="utf-8"?><Airport xmlns:xsi="http://www.w3.org/2001/XMLSchema-instance" xmlns:xsd="http://www.w3.org/2001/XMLSchema"><RunwayLength>1400</RunwayLength><RunwayWidth>300</RunwayWidth><NumberOfRunways>4</NumberOfRunways><Name>Mbf</Name><City>Gomel</City></Airport><?xml version="1.0" encoding="utf-8"?><Airport xmlns:xsi="http://www.w3.org/2001/XMLSchema-instance" xmlns:xsd="http://www.w3.org/2001/XMLSchema"><RunwayLength>1250</RunwayLength><RunwayWidth>310</RunwayWidth><NumberOfRunways>5</NumberOfRunways><Name>Dgf</Name><City>Vitebsk</City></Airport>